vulheader/__init__.py
vulheader/cli.py
vulheader/header_checker.py
vulheader-1.0.1.dist-info/METADATA
vulheader-1.0.1.dist-info/WHEEL
vulheader-1.0.1.dist-info/entry_points.txt
vulheader-1.0.1.dist-info/top_level.txt
vulheader-1.0.1.dist-info/RECORD
