Metadata-Version: 2.1
Name: vulheader
Version: 1.0.1
Summary: A Python tool for checking missing HTTP security headers for better web security.
Home-page: https://mrfidal.in/cyber-security/vulheader
Author: MrFidal
Author-email: mrfidal@proton.me
License: MIT
Project-URL: Documentation, https://mrfidal.in/cyber-security/vulheader
Project-URL: Source, https://github.com/mr-fidal/vulheader
Project-URL: Tracker, https://github.com/mr-fidal/vulheader/issues
Keywords: security headers,web security,HTTP headers,Strict-Transport-Security,Content-Security-Policy,X-Frame-Options,Referrer-Policy,vulnerability scanner,website security
Classifier: Development Status :: 5 - Production/Stable
Classifier: Intended Audience :: Developers
Classifier: Intended Audience :: System Administrators
Classifier: Topic :: Internet :: WWW/HTTP :: HTTP Servers
Classifier: Topic :: Security
Classifier: Programming Language :: Python :: 3
Classifier: Programming Language :: Python :: 3.7
Classifier: Programming Language :: Python :: 3.8
Classifier: Programming Language :: Python :: 3.9
Classifier: Programming Language :: Python :: 3.10
Classifier: License :: OSI Approved :: MIT License
Classifier: Operating System :: OS Independent
Requires-Python: >=3.7
Requires-Dist: requests
Requires-Dist: validlink
